REDCap_LLT/__init__.py
REDCap_LLT/redcap_llt.py
REDCapLLT-3.0.0.dist-info/LICENSE
REDCapLLT-3.0.0.dist-info/METADATA
REDCapLLT-3.0.0.dist-info/WHEEL
REDCapLLT-3.0.0.dist-info/entry_points.txt
REDCapLLT-3.0.0.dist-info/top_level.txt
REDCapLLT-3.0.0.dist-info/RECORD
