Metadata-Version: 2.1
Name: REDCapLLT
Version: 3.0.0
Summary: A package to translate REDCap language libraries
Home-page: https://github.com/gourgiotisw/REDCapLLT
Author: William Gourgiotis
Author-email: william.gourgiotis@umassmed.edu
Classifier: Programming Language :: Python :: 3
Classifier: License :: OSI Approved :: MIT License
Classifier: Operating System :: OS Independent
Requires-Python: >=3.6
License-File: LICENSE
Requires-Dist: googletrans ==4.0.0-rc1
